notifier/__init__.py
notifier/__main__.py
notifier/gpu_monitor.py
notifier/telegram.py
gpu_overseer-0.0.11.dist-info/METADATA
gpu_overseer-0.0.11.dist-info/WHEEL
gpu_overseer-0.0.11.dist-info/dependency_links.txt
gpu_overseer-0.0.11.dist-info/entry_points.txt
gpu_overseer-0.0.11.dist-info/top_level.txt
gpu_overseer-0.0.11.dist-info/RECORD
