Metadata-Version: 2.1
Name: gpu-overseer
Version: 0.0.11
Summary: Telegram notifier for GPU availability status.
Home-page: https://github.com/ViktorooReps/overseer
Author: Viktor Scherbakov
Author-email: viktoroo.sch@gmail.com
License: MIT
Download-URL: https://github.com/ViktorooReps/overseer/archive/0.0.1.tar.gz
Platform: UNKNOWN
Classifier: License :: OSI Approved :: MIT License
Classifier: Programming Language :: Python :: 3
Classifier: Programming Language :: Python :: 3.6
Classifier: Programming Language :: Python :: 3.9
Requires-Python: >=3.6
Requires-Dist: click (==8.1.3)
Requires-Dist: requests (==2.28.1)
Requires-Dist: nvitop (==0.6.2)
